skyagi/__init__.py
skyagi/cli.py
skyagi/config.py
skyagi/context.py
skyagi/model.py
skyagi/settings.py
skyagi/skyagi.py
skyagi/tui.py
skyagi/util.py
skyagi/discord/__init__.py
skyagi/discord/client.py
skyagi/simulation/__init__.py
skyagi/simulation/agent.py
skyagi/simulation/simulation.py
skyagi-0.0.30.dist-info/METADATA
skyagi-0.0.30.dist-info/WHEEL
skyagi-0.0.30.dist-info/entry_points.txt
skyagi-0.0.30.dist-info/top_level.txt
skyagi-0.0.30.dist-info/RECORD
