Metadata-Version: 2.1
Name: skyagi
Version: 0.0.30
Summary: AGI
Home-page: https://github.com/litanlitudan/skyagi
Author: Tan Li
Author-email: tan@tanli.dev
Project-URL: Bug Tracker, https://github.com/litanlitudan/skyagi/issues
Project-URL: Changelog, https://github.com/litanlitudan/skyagi/releases
Classifier: Programming Language :: Python :: 3
Classifier: License :: OSI Approved :: Apache Software License
Classifier: Operating System :: OS Independent
Requires-Python: >=3.8
Requires-Dist: rich
Requires-Dist: textual
Requires-Dist: typer
Requires-Dist: termcolor
Requires-Dist: tiktoken
Requires-Dist: faiss-cpu
Requires-Dist: openai
Requires-Dist: pinecone-client
Requires-Dist: langchain (==0.0.154)
Requires-Dist: discord.py
Requires-Dist: inquirer
Provides-Extra: dev
Requires-Dist: black ; extra == 'dev'
Requires-Dist: Faker ; extra == 'dev'
Requires-Dist: flake8 ; extra == 'dev'
Requires-Dist: isort ; extra == 'dev'
Requires-Dist: memray ; extra == 'dev'
Requires-Dist: pdbpp ; extra == 'dev'
Requires-Dist: pytest ; extra == 'dev'
Requires-Dist: richbench ; extra == 'dev'
